README.rst
setup.py
historical_collection/__init__.py
historical_collection/historical.py
historical_collection.egg-info/PKG-INFO
historical_collection.egg-info/SOURCES.txt
historical_collection.egg-info/dependency_links.txt
historical_collection.egg-info/requires.txt
historical_collection.egg-info/top_level.txt