Metadata-Version: 2.1
Name: historical-collection
Version: 0.1.0
Summary: Easily keep track of changes to Mongo document changes with a collection.
Home-page: https://gitlab.com/srcrr/historical_collection
Author: Jordan Hewitt
Author-email: srcrr@opayq.com
License: MIT
Platform: UNKNOWN
Classifier: Development Status :: 2 - Pre-Alpha
Classifier: License :: OSI Approved :: MIT License
Classifier: Programming Language :: Python
Classifier: Programming Language :: Python :: 2
Classifier: Programming Language :: Python :: 2.7
Classifier: Programming Language :: Python :: 3
Classifier: Programming Language :: Python :: 3.4
Classifier: Programming Language :: Python :: 3.5
Classifier: Programming Language :: Python :: 3.6
Classifier: Programming Language :: Python :: 3.7
